[{"character":"人","category":"People","age":5,"personality":"普通","nationality":"中国","title":"男人","dress":"浅棕色上衣和长裤","action":"一位普通现代中国男性站立微笑，背景简洁","sex":"男","sceneStyle":"摄影风格的水彩画","addStyle":"不同身份的人物","keyWords":""},
{"character":"女","category":"People","age":4,"personality":"温柔","nationality":"中国","title":"女人","dress":"浅粉色连衣裙","action":"一位温柔现代中国女性微笑站立，背景简洁","sex":"女","sceneStyle":"摄影风格的水彩画","addStyle":"不同身份的人物","keyWords":""},
{"character":"子","category":"People","age":3,"personality":"稚嫩","nationality":"中国","title":"男孩","dress":"浅蓝色上衣和短裤","action":"一个稚嫩的男孩开心笑着，背景简洁","sex":"男","sceneStyle":"摄影风格的水彩画","addStyle":"不同身份的人物","keyWords":""},
{"character":"家","category":"People","age":6,"personality":"温馨","nationality":"中国","title":"爸爸","dress":"浅棕色衬衫长裤","action":"一位爸爸抱着孩子，展现家庭的温馨，背景简洁","sex":"男","sceneStyle":"摄影风格的水彩画","addStyle":"不同身份的人物","keyWords":""},
{"character":"男","category":"People","age":5,"personality":"阳刚","nationality":"中国","title":"男人","dress":"浅蓝色衬衫长裤","action":"一位阳刚的现代中国男性微笑站立，背景简洁","sex":"男","sceneStyle":"摄影风格的水彩画","addStyle":"不同身份的人物","keyWords":""},
{"character":"们","category":"People","age":4,"personality":"群体","nationality":"中国","title":"群体","dress":"多样服饰","action":"几位不同年龄的中国人手拉手，表现群体的概念，背景简洁","sex":"","sceneStyle":"摄影风格的水彩画","addStyle":"不同身份的人物","keyWords":""},
{"character":"名","category":"People","age":5,"personality":"著名","nationality":"中国","title":"名人","dress":"深色西装","action":"一位知名人士微笑面对镜头，背景简洁","sex":"男","sceneStyle":"摄影风格的水彩画","addStyle":"不同身份的人物","keyWords":""},
{"character":"姓","category":"People","age":4,"personality":"传统","nationality":"中国","title":"老者","dress":"唐装","action":"一位穿唐装的长者神态庄重，背景简洁","sex":"男","sceneStyle":"摄影风格的水彩画","addStyle":"不同身份的人物","keyWords":""},
{"character":"员","category":"People","age":5,"personality":"职业","nationality":"中国","title":"职员","dress":"衬衫领带","action":"一位职业装女性在工作场景中微笑，背景简洁","sex":"女","sceneStyle":"摄影风格的水彩画","addStyle":"不同身份的人物","keyWords":""},
{"character":"伙","category":"People","age":3,"personality":"伙伴","nationality":"中国","title":"伙伴","dress":"休闲服","action":"两位朋友并肩微笑，表现伙伴关系，背景简洁","sex":"男","sceneStyle":"摄影风格的水彩画","addStyle":"不同身份的人物","keyWords":""},
{"character":"兵","category":"People","age":6,"personality":"英勇","nationality":"中国","title":"士兵","dress":"军装","action":"一位士兵身姿挺拔站立，背景简洁","sex":"男","sceneStyle":"摄影风格的水彩画","addStyle":"不同身份的人物","keyWords":""},
{"character":"王","category":"People","age":5,"personality":"威严","nationality":"中国","title":"国王","dress":"皇冠长袍","action":"一位身穿华服的王者形象，背景简洁","sex":"男","sceneStyle":"摄影风格的水彩画","addStyle":"不同身份的人物","keyWords":""},
{"character":"群","category":"People","age":4,"personality":"聚集","nationality":"中国","title":"人群","dress":"多样服饰","action":"一群不同年龄的中国人站在一起，背景简洁","sex":"","sceneStyle":"摄影风格的水彩画","addStyle":"不同身份的人物","keyWords":""},
{"character":"官","category":"People","age":5,"personality":"正式","nationality":"中国","title":"官员","dress":"制服","action":"一位穿制服的官员微笑，背景简洁","sex":"男","sceneStyle":"摄影风格的水彩画","addStyle":"不同身份的人物","keyWords":""},
{"character":"神","category":"People","age":6,"personality":"神秘","nationality":"中国","title":"神仙","dress":"飘逸长袍","action":"一位仙风道骨的形象遥望远方，背景简洁","sex":"男","sceneStyle":"摄影风格的水彩画","addStyle":"不同身份的人物","keyWords":""},
{"character":"鬼","category":"People","age":4,"personality":"调皮","nationality":"中国","title":"小鬼","dress":"趣味幽灵装","action":"一位扮作可爱幽灵的孩子调皮表情，背景简洁","sex":"男","sceneStyle":"摄影风格的水彩画","addStyle":"不同身份的人物","keyWords":""},
{"character":"党","category":"People","age":5,"personality":"团结","nationality":"中国","title":"党员","dress":"正装","action":"一位佩戴党徽的党员微笑，背景简洁","sex":"男","sceneStyle":"摄影风格的水彩画","addStyle":"不同身份的人物","keyWords":""},
{"character":"佛","category":"People","age":6,"personality":"慈悲","nationality":"中国","title":"佛陀","dress":"僧袍","action":"一位慈悲打坐的僧人形象，背景简洁","sex":"男","sceneStyle":"摄影风格的水彩画","addStyle":"不同身份的人物","keyWords":""},
{"character":"命","category":"People","age":4,"personality":"命运","nationality":"中国","title":"命运之神","dress":"星光袍","action":"一位象征命运智慧的长者形象，背景简洁","sex":"女","sceneStyle":"摄影风格的水彩画","addStyle":"不同身份的人物","keyWords":""},
{"character":"族","category":"People","age":5,"personality":"传承","nationality":"中国","title":"族人","dress":"民族服饰","action":"一位穿民族服饰的族人微笑，背景简洁","sex":"女","sceneStyle":"摄影风格的水彩画","addStyle":"不同身份的人物","keyWords":""},
{"character":"母","category":"People","age":4,"personality":"慈爱","nationality":"中国","title":"母亲","dress":"浅粉色连衣裙","action":"一位慈爱的母亲怀抱婴儿，背景简洁","sex":"女","sceneStyle":"摄影风格的水彩画","addStyle":"不同身份的人物","keyWords":""},
{"character":"组","category":"People","age":5,"personality":"协作","nationality":"中国","title":"组员","dress":"统一服饰","action":"几位统一服装的团队成员微笑合影，背景简洁","sex":"","sceneStyle":"摄影风格的水彩画","addStyle":"不同身份的人物","keyWords":""},
{"character":"丁","category":"People","age":3,"personality":"普通","nationality":"中国","title":"男丁","dress":"浅棕色上衣","action":"一位普通男丁在田间微笑，背景简洁","sex":"男","sceneStyle":"摄影风格的水彩画","addStyle":"不同身份的人物","keyWords":""},
{"character":"伴","category":"People","age":4,"personality":"陪伴","nationality":"中国","title":"伙伴","dress":"休闲服","action":"两位伙伴相互扶持微笑，背景简洁","sex":"女","sceneStyle":"摄影风格的水彩画","addStyle":"不同身份的人物","keyWords":""},
{"character":"姨","category":"People","age":5,"personality":"亲切","nationality":"中国","title":"阿姨","dress":"花色连衣裙","action":"一位和蔼阿姨在厨房微笑，背景简洁","sex":"女","sceneStyle":"摄影风格的水彩画","addStyle":"不同身份的人物","keyWords":""},
{"character":"娘","category":"People","age":6,"personality":"朴实","nationality":"中国","title":"姑娘","dress":"布衣","action":"一位淳朴姑娘在作坊劳作，背景简洁","sex":"女","sceneStyle":"摄影风格的水彩画","addStyle":"不同身份的人物","keyWords":""},
{"character":"贼","category":"People","age":4,"personality":"狡黠","nationality":"中国","title":"小贼","dress":"条纹服","action":"一位扮作小贼的演员调皮眨眼，背景简洁","sex":"男","sceneStyle":"摄影风格的水彩画","addStyle":"不同身份的人物","keyWords":""},
{"character":"魂","category":"People","age":5,"personality":"飘渺","nationality":"中国","title":"灵魂","dress":"半透明长袍","action":"一位象征灵魂的飘逸形象静立，背景简洁","sex":"男","sceneStyle":"摄影风格的水彩画","addStyle":"不同身份的人物","keyWords":""}]